promoterai/__init__.py
promoterai/architecture.py
promoterai/finetune.py
promoterai/generator.py
promoterai/preprocess.py
promoterai/score.py
promoterai/tfrecords.py
promoterai/train.py
promoterai/utils.py
promoterai-1.0rc6.dist-info/licenses/LICENSE
promoterai-1.0rc6.dist-info/METADATA
promoterai-1.0rc6.dist-info/WHEEL
promoterai-1.0rc6.dist-info/entry_points.txt
promoterai-1.0rc6.dist-info/top_level.txt
promoterai-1.0rc6.dist-info/RECORD
