Metadata-Version: 2.4
Name: promoterai
Version: 1.0rc6
Summary: Predict the impact of promoter variants on gene expression
Home-page: https://github.com/Illumina/PromoterAI
Author: Kishore Jaganathan
Author-email: kishorejaganathan@gmail.com
License: PolyForm Strict License 1.0.0
Requires-Python: >=3.8
License-File: LICENSE
Requires-Dist: numpy>=1.20
Requires-Dist: pandas>=2.0
Requires-Dist: pyfaidx>=0.8
Requires-Dist: pybigwig>=0.3
Requires-Dist: tensorflow<2.16,>=2.13
Requires-Dist: keras<3.0,>=2.13
Dynamic: author
Dynamic: author-email
Dynamic: description
Dynamic: description-content-type
Dynamic: home-page
Dynamic: license
Dynamic: license-file
Dynamic: requires-dist
Dynamic: requires-python
Dynamic: summary
